opticlp/__init__.py
opticlp/modules/__init__.py
opticlp/py.typed
opticlp/routines/__init__.py
opticlp-0.1.8.dist-info/WHEEL
opticlp-0.1.8.dist-info/METADATA
opticlp-0.1.8.dist-info/RECORD
