Metadata-Version: 2.3
Name: opticlp
Version: 0.1.8
Summary: A library that calculates simple calculations for optical alignments.
Requires-Dist: corelp
Requires-Python: >=3.12
